dimed_2/__init__.py
dimed_2/cli.py
dimed_2-0.2.dist-info/METADATA
dimed_2-0.2.dist-info/WHEEL
dimed_2-0.2.dist-info/entry_points.txt
dimed_2-0.2.dist-info/top_level.txt
dimed_2-0.2.dist-info/RECORD
