Metadata-Version: 2.1
Name: dimed_2
Version: 0.2
Summary: Circular dependencies check
Author-email: Dmitry Sorokin <dmd40in@gmail.com>
Requires-Dist: click
Requires-Dist: dimed
